axcent/__init__.py
axcent/core.py
axcent/history.py
axcent/llm.py
axcent/media.py
axcent/tools.py
axcent-0.3.0.dist-info/licenses/LICENSE
axcent-0.3.0.dist-info/METADATA
axcent-0.3.0.dist-info/WHEEL
axcent-0.3.0.dist-info/top_level.txt
axcent-0.3.0.dist-info/RECORD
