Metadata-Version: 2.4
Name: axcent
Version: 0.3.0
Summary: The easiest way to build AI agents in Python
Home-page: https://github.com/ssshiponu/axcent
Author: Mohin Uddin Shipon
Author-email: sshiponudin22@gmail.com
Classifier: Programming Language :: Python :: 3
Classifier: License :: OSI Approved :: MIT License
Classifier: Operating System :: OS Independent
Requires-Python: >=3.8
License-File: LICENSE
Requires-Dist: openai>=1.0.0
Requires-Dist: python-dotenv>=1.0.0
Provides-Extra: gemini
Requires-Dist: google-genai>=1.57.0; extra == "gemini"
Dynamic: author
Dynamic: author-email
Dynamic: classifier
Dynamic: description
Dynamic: description-content-type
Dynamic: home-page
Dynamic: license-file
Dynamic: provides-extra
Dynamic: requires-dist
Dynamic: requires-python
Dynamic: summary
